django_minio_backend/__init__.py
django_minio_backend/apps.py
django_minio_backend/models.py
django_minio_backend/tests.py
django_minio_backend/utils.py
django_minio_backend/management/__init__.py
django_minio_backend/management/commands/__init__.py
django_minio_backend/management/commands/clean_orphaned_minio_files.py
django_minio_backend/management/commands/initialize_buckets.py
django_minio_backend/management/commands/is_minio_available.py
django_minio_backend-4.4.3.dist-info/METADATA
django_minio_backend-4.4.3.dist-info/WHEEL
django_minio_backend-4.4.3.dist-info/licenses/LICENSE
django_minio_backend-4.4.3.dist-info/RECORD
