Metadata-Version: 2.4
Name: django-minio-backend
Version: 4.4.3
Summary: The django-minio-backend provides a wrapper around the MinIO Python Library.
Project-URL: Homepage, https://github.com/theriverman/django-minio-backend
Project-URL: Repository, https://github.com/theriverman/django-minio-backend
Author-email: "Kristof Daja (theriverman)" <22156894+theriverman@users.noreply.github.com>
License: MIT
License-File: LICENSE
Classifier: Environment :: Web Environment
Classifier: Framework :: Django
Classifier: Framework :: Django :: 4.2
Classifier: Framework :: Django :: 5.0
Classifier: Framework :: Django :: 5.1
Classifier: Framework :: Django :: 5.2
Classifier: Intended Audience :: Developers
Classifier: License :: OSI Approved :: MIT License
Classifier: Operating System :: OS Independent
Classifier: Programming Language :: Python
Classifier: Programming Language :: Python :: 3.11
Classifier: Programming Language :: Python :: 3.12
Classifier: Programming Language :: Python :: 3.13
Classifier: Programming Language :: Python :: 3.14
Classifier: Topic :: Internet :: WWW/HTTP :: Dynamic Content
Classifier: Topic :: Internet :: WWW/HTTP :: Dynamic Content :: Content Management System
Classifier: Topic :: Internet :: WWW/HTTP :: WSGI :: Application
Requires-Python: >=3.11
Requires-Dist: django>=4.2
Requires-Dist: minio==7.2.19
Requires-Dist: pillow>=10.0.0
